[
  {
    "url": "https://www.facebook.com/events/1186908029002432/",
    "date": "Tue 28.5.",
    "start": "18:00",
    "end": "21:30",
    "location": "Kalasatamanpuisto",
    "styles": [
      "bachata"
    ]
  },
  {
    "url": "https://www.facebook.com/events/1482881985955113/",
    "date": "Thu 30.5.",
    "start": "18:00",
    "end": "22:30",
    "location": "Oopperan amfiteatteri",
    "styles": [
      "bachata"
    ]
  },
  {
    "url": "https://www.facebook.com/events/812422340781005/",
    "date": "Fri 31.5.",
    "start": "19:15",
    "end": "01:00",
    "location": "Helsinki Dance Central",
    "styles": [
      "urbankiz"
    ],
    "price": "🔹 5€ for social (cash only)\n🔹 20€ for class + social, pay at helsbk.org/pay"
  }
]
